py_splash/__init__.py
py_splash/driver.py
py_splash/exceptions.py
py_splash/static.py
py_splash-0.4.5.dist-info/DESCRIPTION.rst
py_splash-0.4.5.dist-info/METADATA
py_splash-0.4.5.dist-info/RECORD
py_splash-0.4.5.dist-info/WHEEL
py_splash-0.4.5.dist-info/metadata.json
py_splash-0.4.5.dist-info/top_level.txt
