Metadata-Version: 2.0
Name: py-splash
Version: 0.4.5
Summary: Small interface for splash written in python.
Home-page: https://github.com/postalXdude/PySplash
Author: Nikola Jasek
Author-email: nikolajasek1@gmail.com
License: UNKNOWN
Download-URL: https://github.com/postalXdude/PySplash/archive/0.4.5.tar.gz
Keywords: web scraping,splash,dryscrape,ghost.py,dynamic web pages,webkit,phantomjs,evaluate javascript,selenium
Platform: UNKNOWN
Classifier: Programming Language :: Python :: 2
Classifier: Programming Language :: Python :: 3
Classifier: Topic :: Software Development :: Code Generators
Classifier: Intended Audience :: Developers
Classifier: Operating System :: MacOS
Classifier: Operating System :: Unix
Classifier: Operating System :: Microsoft :: Windows
Classifier: Topic :: Utilities
